[
  {
    "id": "bj_plastics_hospital",
    "name": "北京大学第三医院（整形外科）",
    "province": "北京",
    "city": "北京",
    "address": "北京市海淀区花园北路49号",
    "phone": "010-82266699",
    "latitude": 39.9811,
    "longitude": 116.3513,
    "departments": ["surgery", "psychiatry", "endocrinology"],
    "tags": ["SRS", "HRT", "诊断证明"],
    "doctors": [
      { "name": "潘柏林", "title": "主任医师", "notes": "性别重置手术" },
      { "name": "赵润泽", "title": "副主任医师", "notes": "面部女性化手术" }
    ],
    "notes": "国内较早开展性别重置手术的三甲医院之一，经验丰富。",
    "sourceUrl": "https://mtf.wiki/zh-cn/med/hospital/bj/plastics/"
  },
  {
    "id": "bj_anxiety_hospital",
    "name": "北京大学第六医院（精神科）",
    "province": "北京",
    "city": "北京",
    "address": "北京市海淀区花园北路51号",
    "phone": "010-82801999",
    "latitude": 39.9814,
    "longitude": 116.3503,
    "departments": ["psychiatry"],
    "tags": ["诊断证明", "心理咨询"],
    "notes": "全国精神卫生领域权威医院，可开具易性症诊断证明。",
    "sourceUrl": "https://mtf.wiki/zh-cn/med/hospital/bj/pku6/"
  },
  {
    "id": "sh_9th_hospital",
    "name": "上海第九人民医院（整复外科）",
    "province": "上海",
    "city": "上海",
    "address": "上海市黄浦区制造局路639号",
    "phone": "021-23271699",
    "latitude": 31.2069,
    "longitude": 121.4824,
    "departments": ["surgery", "voice"],
    "tags": ["SRS", "FFS", "嗓音手术"],
    "notes": "上海权威整形外科医院，可进行性别重置手术、面部女性化手术。",
    "sourceUrl": "https://mtf.wiki/zh-cn/med/hospital/sh/9th/"
  },
  {
    "id": "sh_mental_health_center",
    "name": "上海市精神卫生中心",
    "province": "上海",
    "city": "上海",
    "address": "上海市徐汇区宛平南路600号",
    "phone": "021-34289888",
    "latitude": 31.1877,
    "longitude": 121.4398,
    "departments": ["psychiatry"],
    "tags": ["诊断证明", "心理咨询"],
    "sourceUrl": "https://mtf.wiki/zh-cn/med/hospital/sh/mental/"
  },
  {
    "id": "gz_zhujiang_hospital",
    "name": "南方医科大学珠江医院",
    "province": "广东",
    "city": "广州",
    "address": "广东省广州市海珠区工业大道中253号",
    "phone": "020-61641114",
    "latitude": 23.0868,
    "longitude": 113.2737,
    "departments": ["endocrinology", "psychiatry", "surgery"],
    "tags": ["HRT", "诊断证明", "SRS"],
    "notes": "可开具诊断证明和HRT处方。",
    "sourceUrl": "https://mtf.wiki/zh-cn/med/hospital/gz/zhujiang/"
  },
  {
    "id": "sz_people_hospital",
    "name": "深圳市人民医院",
    "province": "广东",
    "city": "深圳",
    "address": "广东省深圳市罗湖区东门北路1017号",
    "phone": "0755-25533018",
    "latitude": 22.5465,
    "longitude": 114.1232,
    "departments": ["endocrinology", "psychiatry"],
    "tags": ["HRT", "诊断证明"],
    "sourceUrl": "https://mtf.wiki/zh-cn/med/hospital/sz/people/"
  },
  {
    "id": "cd_huaixi_clinic",
    "name": "成都市第四人民医院（精神科）",
    "province": "四川",
    "city": "成都",
    "address": "四川省成都市金牛区营门口路互利西一巷8号",
    "phone": "028-87528604",
    "latitude": 30.6881,
    "longitude": 104.0301,
    "departments": ["psychiatry"],
    "tags": ["诊断证明", "心理咨询"],
    "notes": "成都市精神卫生中心，可开具易性症诊断证明。",
    "sourceUrl": "https://mtf.wiki/zh-cn/med/hospital/cd/4th/"
  },
  {
    "id": "cd_west_china",
    "name": "四川大学华西医院",
    "province": "四川",
    "city": "成都",
    "address": "四川省成都市武侯区国学巷37号",
    "phone": "028-85422114",
    "latitude": 30.6430,
    "longitude": 104.0531,
    "departments": ["endocrinology", "psychiatry", "surgery"],
    "tags": ["HRT", "诊断证明", "SRS"],
    "notes": "西南地区综合实力最强的医院之一。",
    "sourceUrl": "https://mtf.wiki/zh-cn/med/hospital/cd/westchina/"
  },
  {
    "id": "wh_people_hospital",
    "name": "武汉大学人民医院",
    "province": "湖北",
    "city": "武汉",
    "address": "湖北省武汉市武昌区解放路238号",
    "phone": "027-88041911",
    "latitude": 30.5458,
    "longitude": 114.3109,
    "departments": ["psychiatry", "endocrinology"],
    "tags": ["诊断证明", "HRT"],
    "notes": "可开具易性症诊断证明。",
    "sourceUrl": "https://mtf.wiki/zh-cn/med/hospital/wh/people/"
  },
  {
    "id": "hz_1st_hospital",
    "name": "浙江大学医学院附属第一医院",
    "province": "浙江",
    "city": "杭州",
    "address": "浙江省杭州市上城区庆春路79号",
    "phone": "0571-87236666",
    "latitude": 30.2613,
    "longitude": 120.1703,
    "departments": ["endocrinology", "psychiatry"],
    "tags": ["HRT", "诊断证明"],
    "sourceUrl": "https://mtf.wiki/zh-cn/med/hospital/hz/1st/"
  },
  {
    "id": "nj_drum_tower",
    "name": "南京鼓楼医院",
    "province": "江苏",
    "city": "南京",
    "address": "江苏省南京市鼓楼区中山路321号",
    "phone": "025-83106666",
    "latitude": 32.0536,
    "longitude": 118.7807,
    "departments": ["endocrinology", "psychiatry"],
    "tags": ["HRT", "诊断证明"],
    "sourceUrl": "https://mtf.wiki/zh-cn/med/hospital/nj/drumtower/"
  },
  {
    "id": "cs_xiangya_2nd",
    "name": "中南大学湘雅二医院",
    "province": "湖南",
    "city": "长沙",
    "address": "湖南省长沙市芙蓉区人民中路139号",
    "phone": "0731-85295999",
    "latitude": 28.1902,
    "longitude": 113.0052,
    "departments": ["psychiatry", "endocrinology"],
    "tags": ["诊断证明", "HRT"],
    "sourceUrl": "https://mtf.wiki/zh-cn/med/hospital/cs/xiangya2/"
  },
  {
    "id": "cq_1st_hospital",
    "name": "重庆医科大学附属第一医院",
    "province": "重庆",
    "city": "重庆",
    "address": "重庆市渝中区袁家岗友谊路1号",
    "phone": "023-89012222",
    "latitude": 29.5358,
    "longitude": 106.5107,
    "departments": ["endocrinology", "psychiatry"],
    "tags": ["HRT", "诊断证明"],
    "sourceUrl": "https://mtf.wiki/zh-cn/med/hospital/cq/1st/"
  },
  {
    "id": "xa_1st_hospital",
    "name": "西安交通大学第一附属医院",
    "province": "陕西",
    "city": "西安",
    "address": "陕西省西安市雁塔区雁塔西路277号",
    "phone": "029-85323338",
    "latitude": 34.2012,
    "longitude": 108.9322,
    "departments": ["endocrinology", "psychiatry"],
    "tags": ["HRT", "诊断证明"],
    "sourceUrl": "https://mtf.wiki/zh-cn/med/hospital/xa/1st/"
  },
  {
    "id": "km_1st_hospital",
    "name": "昆明医科大学第一附属医院",
    "province": "云南",
    "city": "昆明",
    "address": "云南省昆明市五华区西昌路295号",
    "phone": "0871-65324888",
    "latitude": 25.0374,
    "longitude": 102.7014,
    "departments": ["endocrinology", "psychiatry"],
    "tags": ["HRT", "诊断证明"],
    "notes": "云南省可做HRT和诊断证明的重要医院。",
    "sourceUrl": "https://mtf.wiki/zh-cn/med/hospital/km/1st/"
  },
  {
    "id": "heb_1st_hospital",
    "name": "哈尔滨医科大学附属第一医院",
    "province": "黑龙江",
    "city": "哈尔滨",
    "address": "黑龙江省哈尔滨市南岗区邮政街23号",
    "phone": "0451-85555111",
    "latitude": 45.7688,
    "longitude": 126.6371,
    "departments": ["endocrinology", "psychiatry"],
    "tags": ["HRT", "诊断证明"],
    "sourceUrl": "https://mtf.wiki/zh-cn/med/hospital/heb/1st/"
  },
  {
    "id": "sy_1st_hospital",
    "name": "中国医科大学附属第一医院",
    "province": "辽宁",
    "city": "沈阳",
    "address": "辽宁省沈阳市和平区南京北街155号",
    "phone": "024-83283333",
    "latitude": 41.7930,
    "longitude": 123.4149,
    "departments": ["endocrinology", "psychiatry"],
    "tags": ["HRT", "诊断证明"],
    "sourceUrl": "https://mtf.wiki/zh-cn/med/hospital/sy/1st/"
  },
  {
    "id": "bj_zxl_laser",
    "name": "北京知心庐医疗美容诊所",
    "province": "北京",
    "city": "北京",
    "address": "北京市朝阳区建国路88号SOHO现代城",
    "latitude": 39.9035,
    "longitude": 116.4604,
    "departments": ["laser", "general"],
    "tags": ["激光脱毛", "面部护理"],
    "notes": "跨性别友好诊所，提供激光脱毛等服务。",
    "sourceUrl": "https://mtf.wiki/zh-cn/med/hospital/bj/laser/"
  },
  {
    "id": "sh_huashan_hospital",
    "name": "复旦大学附属华山医院（皮肤科）",
    "province": "上海",
    "city": "上海",
    "address": "上海市静安区乌鲁木齐中路12号",
    "phone": "021-52889999",
    "latitude": 31.2172,
    "longitude": 121.4423,
    "departments": ["dermatology", "laser"],
    "tags": ["激光脱毛", "皮肤科"],
    "sourceUrl": "https://mtf.wiki/zh-cn/med/hospital/sh/huashan/"
  },
  {
    "id": "bj_union_hospital",
    "name": "中国医学科学院北京协和医院（内分泌科）",
    "province": "北京",
    "city": "北京",
    "address": "北京市东城区东单北大街53号",
    "phone": "010-69156114",
    "latitude": 39.9147,
    "longitude": 116.4132,
    "departments": ["endocrinology"],
    "tags": ["HRT"],
    "notes": "全国内分泌领域权威，可以开具HRT处方。",
    "sourceUrl": "https://mtf.wiki/zh-cn/med/hospital/bj/pumc/"
  },
  {
    "id": "sh_changhai_hospital",
    "name": "海军军医大学第二附属医院（上海长征医院）",
    "province": "上海",
    "city": "上海",
    "address": "上海市黄浦区凤阳路415号",
    "phone": "021-81886999",
    "latitude": 31.2267,
    "longitude": 121.4688,
    "departments": ["surgery"],
    "tags": ["SRS"],
    "sourceUrl": "https://mtf.wiki/zh-cn/med/hospital/sh/changhai/"
  },
  {
    "id": "wh_tongji_hospital",
    "name": "华中科技大学同济医学院附属同济医院",
    "province": "湖北",
    "city": "武汉",
    "address": "湖北省武汉市硚口区解放大道1095号",
    "phone": "027-83662688",
    "latitude": 30.5793,
    "longitude": 114.2588,
    "departments": ["endocrinology", "psychiatry", "surgery"],
    "tags": ["HRT", "诊断证明", "SRS"],
    "sourceUrl": "https://mtf.wiki/zh-cn/med/hospital/wh/tongji/"
  },
  {
    "id": "gz_sun_yat_sen",
    "name": "中山大学附属第三医院",
    "province": "广东",
    "city": "广州",
    "address": "广东省广州市天河区天河路600号",
    "phone": "020-85253111",
    "latitude": 23.1305,
    "longitude": 113.3342,
    "departments": ["endocrinology", "psychiatry"],
    "tags": ["HRT", "诊断证明"],
    "sourceUrl": "https://mtf.wiki/zh-cn/med/hospital/gz/sysu3/"
  },
  {
    "id": "fz_union_hospital",
    "name": "福建医科大学附属协和医院",
    "province": "福建",
    "city": "福州",
    "address": "福建省福州市鼓楼区新权路29号",
    "phone": "0591-86218120",
    "latitude": 26.0728,
    "longitude": 119.3049,
    "departments": ["endocrinology", "psychiatry"],
    "tags": ["HRT", "诊断证明"],
    "sourceUrl": "https://mtf.wiki/zh-cn/med/hospital/fz/union/"
  },
  {
    "id": "jn_ql_hospital",
    "name": "山东大学齐鲁医院",
    "province": "山东",
    "city": "济南",
    "address": "山东省济南市历下区文化西路107号",
    "phone": "0531-82169114",
    "latitude": 36.6531,
    "longitude": 117.0307,
    "departments": ["endocrinology", "psychiatry"],
    "tags": ["HRT", "诊断证明"],
    "sourceUrl": "https://mtf.wiki/zh-cn/med/hospital/jn/ql/"
  },
  {
    "id": "hf_1st_hospital",
    "name": "安徽医科大学第一附属医院",
    "province": "安徽",
    "city": "合肥",
    "address": "安徽省合肥市蜀山区绩溪路218号",
    "phone": "0551-62922114",
    "latitude": 31.8444,
    "longitude": 117.2720,
    "departments": ["endocrinology", "psychiatry"],
    "tags": ["HRT", "诊断证明"],
    "sourceUrl": "https://mtf.wiki/zh-cn/med/hospital/hf/1st/"
  },
  {
    "id": "nc_2nd_hospital",
    "name": "南昌大学第二附属医院",
    "province": "江西",
    "city": "南昌",
    "address": "江西省南昌市东湖区民德路1号",
    "phone": "0791-86311222",
    "latitude": 28.6780,
    "longitude": 115.8871,
    "departments": ["endocrinology", "psychiatry"],
    "tags": ["HRT", "诊断证明"],
    "sourceUrl": "https://mtf.wiki/zh-cn/med/hospital/nc/2nd/"
  },
  {
    "id": "nn_1st_hospital",
    "name": "广西医科大学第一附属医院",
    "province": "广西",
    "city": "南宁",
    "address": "广西南宁市青秀区双拥路6号",
    "phone": "0771-5356563",
    "latitude": 22.7955,
    "longitude": 108.3568,
    "departments": ["endocrinology", "psychiatry"],
    "tags": ["HRT", "诊断证明"],
    "sourceUrl": "https://mtf.wiki/zh-cn/med/hospital/nn/1st/"
  },
  {
    "id": "sh_laser_clinic",
    "name": "上海仁爱医院（皮肤美容科）",
    "province": "上海",
    "city": "上海",
    "address": "上海市徐汇区漕溪路133号",
    "phone": "021-64688888",
    "latitude": 31.1767,
    "longitude": 121.4368,
    "departments": ["laser", "dermatology"],
    "tags": ["激光脱毛", "皮肤美容"],
    "notes": "提供激光脱毛服务，对跨性别者友好。",
    "sourceUrl": "https://mtf.wiki/zh-cn/med/hospital/sh/laser/"
  },
  {
    "id": "cd_vocal_clinic",
    "name": "四川大学华西医院（耳鼻喉科-嗓音）",
    "province": "四川",
    "city": "成都",
    "address": "四川省成都市武侯区国学巷37号",
    "phone": "028-85422114",
    "latitude": 30.6430,
    "longitude": 104.0531,
    "departments": ["voice"],
    "tags": ["嗓音训练", "嗓音手术"],
    "notes": "可进行嗓音女性化手术及嗓音训练指导。",
    "sourceUrl": "https://mtf.wiki/zh-cn/med/hospital/cd/voice/"
  },
  {
    "id": "bj_voice_clinic",
    "name": "北京友谊医院（耳鼻喉科）",
    "province": "北京",
    "city": "北京",
    "address": "北京市西城区永安路95号",
    "phone": "010-63138432",
    "latitude": 39.8845,
    "longitude": 116.3854,
    "departments": ["voice"],
    "tags": ["嗓音训练", "嗓音手术"],
    "notes": "可进行嗓音女性化手术评估。",
    "sourceUrl": "https://mtf.wiki/zh-cn/med/hospital/bj/voice/"
  },
  {
    "id": "xm_1st_hospital",
    "name": "厦门大学附属第一医院",
    "province": "福建",
    "city": "厦门",
    "address": "福建省厦门市思明区镇海路55号",
    "phone": "0592-2137111",
    "latitude": 24.4547,
    "longitude": 118.0894,
    "departments": ["endocrinology", "psychiatry"],
    "tags": ["HRT", "诊断证明"],
    "sourceUrl": "https://mtf.wiki/zh-cn/med/hospital/xm/1st/"
  },
  {
    "id": "tj_general_hospital",
    "name": "天津医科大学总医院",
    "province": "天津",
    "city": "天津",
    "address": "天津市和平区鞍山道154号",
    "phone": "022-60362255",
    "latitude": 39.1183,
    "longitude": 117.1764,
    "departments": ["endocrinology", "psychiatry"],
    "tags": ["HRT", "诊断证明"],
    "sourceUrl": "https://mtf.wiki/zh-cn/med/hospital/tj/general/"
  },
  {
    "id": "zz_1st_hospital",
    "name": "郑州大学第一附属医院",
    "province": "河南",
    "city": "郑州",
    "address": "河南省郑州市二七区建设东路1号",
    "phone": "0371-66913114",
    "latitude": 34.7528,
    "longitude": 113.6518,
    "departments": ["endocrinology", "psychiatry"],
    "tags": ["HRT", "诊断证明"],
    "sourceUrl": "https://mtf.wiki/zh-cn/med/hospital/zz/1st/"
  },
  {
    "id": "sz_hk_university_hospital",
    "name": "香港大学深圳医院",
    "province": "广东",
    "city": "深圳",
    "address": "广东省深圳市福田区海园一路1号",
    "phone": "0755-86913333",
    "latitude": 22.5226,
    "longitude": 114.0128,
    "departments": ["psychiatry", "endocrinology"],
    "tags": ["HRT", "诊断证明"],
    "notes": "国际化管理模式，跨性别友好度高。",
    "sourceUrl": "https://mtf.wiki/zh-cn/med/hospital/sz/hku/"
  }
]
